{
	"configurations" : 
	[
		{
			"directories" : 
			[
				{
					"build" : ".",
					"jsonFile" : "directory-.-Debug-f5ebdc15457944623624.json",
					"minimumCMakeVersion" : 
					{
						"string" : "3.0"
					},
					"projectIndex" : 0,
					"source" : ".",
					"targetIndexes" : 
					[
						0
					]
				}
			],
			"name" : "Debug",
			"projects" : 
			[
				{
					"directoryIndexes" : 
					[
						0
					],
					"name" : "tinyraytracer",
					"targetIndexes" : 
					[
						0
					]
				}
			],
			"targets" : 
			[
				{
					"directoryIndex" : 0,
					"id" : "tinyraytracer::@6890427a1f51a3e7e1df",
					"jsonFile" : "target-tinyraytracer-Debug-9ba7824a235e5ae94468.json",
					"name" : "tinyraytracer",
					"projectIndex" : 0
				}
			]
		}
	],
	"kind" : "codemodel",
	"paths" : 
	{
		"build" : "/home/guy/Documents/Semestre_8/Moteur_3D/project_renderer/build",
		"source" : "/home/guy/Documents/Semestre_8/Moteur_3D/project_renderer"
	},
	"version" : 
	{
		"major" : 2,
		"minor" : 3
	}
}
